scorechecker/__init__.py
scorechecker/auth.py
scorechecker/base.py
scorechecker/config.py
scorechecker/loader.py
scorechecker/main.py
scorechecker/result.py
scorechecker/course/__init__.py
scorechecker/course/extract.py
scorechecker/course/optimize.py
scorechecker/course/query.py
scorechecker/course/score.py
scorechecker/image/__init__.py
scorechecker/image/partition.py
scorechecker/image/predict.py
scorechecker/image/process.py
scorechecker/net/__init__.py
scorechecker/net/analyze.py
scorechecker/net/cookies.py
scorechecker/net/headers.py
scorechecker/net/message.py
scorechecker/util/__init__.py
scorechecker/util/check.py
scorechecker/util/cryptography.py
WHU_ScoreChecker-1.0.2.dist-info/LICENSE
WHU_ScoreChecker-1.0.2.dist-info/METADATA
WHU_ScoreChecker-1.0.2.dist-info/WHEEL
WHU_ScoreChecker-1.0.2.dist-info/entry_points.txt
WHU_ScoreChecker-1.0.2.dist-info/top_level.txt
WHU_ScoreChecker-1.0.2.dist-info/RECORD
