Metadata-Version: 2.1
Name: WHU-ScoreChecker
Version: 1.0.2
Summary: A simple, open-source and model-driven score checker for WHU.
Home-page: https://github.com/T0nyX1ang/WHU-ScoreChecker
Author: Tony Xiang
Author-email: tonyxfy@qq.com
License: MIT
Platform: UNKNOWN
Classifier: Programming Language :: Python :: 3.5
Classifier: Programming Language :: Python :: 3.6
Classifier: Programming Language :: Python :: 3.7
Classifier: License :: OSI Approved :: MIT License
Classifier: Operating System :: Microsoft :: Windows
Classifier: Development Status :: 4 - Beta
Requires-Python: >=3.5, <3.8
Requires-Dist: Keras (>=2.3.1)
Requires-Dist: lxml (>=4.3.2)
Requires-Dist: opencv-python (>=4.1.0.25)
Requires-Dist: keyring (>=20.0.1)
Requires-Dist: requests (>=2.21.0)
Requires-Dist: numpy (>=1.16.2)
Requires-Dist: pycryptodome (>=3.9.6)
Requires-Dist: beautifulsoup4 (>=4.7.1)
Requires-Dist: tensorflow (==2.0.1)
